README
setup.py
Checkpoint.egg-info/PKG-INFO
Checkpoint.egg-info/SOURCES.txt
Checkpoint.egg-info/dependency_links.txt
Checkpoint.egg-info/entry_points.txt
Checkpoint.egg-info/top_level.txt
checkpoint/__init__.py
checkpoint/command.py
checkpoint/database.py
checkpoint/error.py
checkpoint/filestore.py
checkpoint/manager.py
checkpoint/repository.py
checkpoint/util.py
checkpoint/release/__init__.py
checkpoint/release/googlecode_upload.py
checkpoint/tests/__init__.py
checkpoint/tests/database.py
checkpoint/tests/filestore.py
checkpoint/tests/repository.py
checkpoint/tests/util.py