Metadata-Version: 1.0
Name: Checkpoint
Version: 0.1
Summary: Checkpoint is a simple media archive management system.
Home-page: http://checkpoint.googlecode.com/
Author: Ian Charnas
Author-email: ian.charnas@gmail.com
License: UNKNOWN
Download-URL: http://code.google.com/p/checkpoint/downloads/list
Keywords: checkpoint,version control
Platform: UNKNOWN
Classifier: Environment :: Console
Classifier: Environment :: Plugins
Classifier: Intended Audience :: Developers
Classifier: Intended Audience :: End Users/Desktop
Classifier: License :: OSI Approved :: BSD License
Classifier: Operating System :: OS Independent
Classifier: Programming Language :: Python
Classifier: Topic :: Software Development :: Libraries :: Python Modules
Classifier: Topic :: Software Development :: Version Control
Classifier: Topic :: System :: Archiving
Classifier: Topic :: Utilities
